wcap_core.cp310-win_amd64.pyd
wcap/__init__.py
wcap/wcap.py
window_capture_audio_py-0.0.3.dist-info/METADATA
window_capture_audio_py-0.0.3.dist-info/WHEEL
window_capture_audio_py-0.0.3.dist-info/top_level.txt
window_capture_audio_py-0.0.3.dist-info/RECORD
